sdrdm_database/__init__.py
sdrdm_database/cli.py
sdrdm_database/commands.py
sdrdm_database/dataio.py
sdrdm_database/dbconnector.py
sdrdm_database/graphql.py
sdrdm_database/modelutils.py
sdrdm_database/tablecreator.py
sdrdm_database/tableutils.py
sdrdm_database-0.4.1.dist-info/LICENSE
sdrdm_database-0.4.1.dist-info/METADATA
sdrdm_database-0.4.1.dist-info/WHEEL
sdrdm_database-0.4.1.dist-info/entry_points.txt
sdrdm_database-0.4.1.dist-info/RECORD
