Metadata-Version: 2.1
Name: sdrdm_database
Version: 0.4.1
Summary: An sdRDM-based framework to utilize databases
License: MIT
Author: Jan Range
Author-email: 30547301+JR-1991@users.noreply.github.com
Requires-Python: >=3.9,<4.0
Classifier: License :: OSI Approved :: MIT License
Classifier: Programming Language :: Python :: 3
Classifier: Programming Language :: Python :: 3.9
Classifier: Programming Language :: Python :: 3.10
Classifier: Programming Language :: Python :: 3.11
Provides-Extra: mysql
Provides-Extra: postgres
Requires-Dist: gitpython (>=3.1.40,<4.0.0)
Requires-Dist: ibis-framework[mysql] (>=7.0.0,<8.0.0)
Requires-Dist: joblib (>=1.3.2,<2.0.0)
Requires-Dist: pydantic (==1.10)
Requires-Dist: strawberry-graphql (>=0.209.8,<0.210.0)
Requires-Dist: typer (>=0.9.0,<0.10.0)
Requires-Dist: validators (>=0.22.0,<0.23.0)
